[{"nombre":"Nikola","apellido":"Jokic","ppp":0.0,"nota":32.94,"salario":33.0},{"nombre":"Russell","apellido":"Westbrook","ppp":0.0,"nota":15.01,"salario":45.0},{"nombre":"Stephen","apellido":"Curry","ppp":0.0,"nota":21.47,"salario":42.0},{"nombre":"Jordan","apellido":"Poole","ppp":0.0,"nota":16.2,"salario":3.0},{"nombre":"Luka","apellido":"Doncic","ppp":0.0,"nota":25.13,"salario":37.0},{"nombre":"Andrew","apellido":"Wigging","ppp":0.0,"nota":15.04,"salario":36.0},{"nombre":"Tyler","apellido":"Herro","ppp":0.0,"nota":16.3,"salario":14.0}]